scrapegen/__init__.py
scrapegen/config.py
scrapegen/exceptions.py
scrapegen/scraper_main.py
scrapegen/__pycache__/__init__.cpython-311.pyc
scrapegen/__pycache__/config.cpython-311.pyc
scrapegen/__pycache__/exceptions.cpython-311.pyc
scrapegen/__pycache__/scraper_main.cpython-311.pyc
scrapegen/extractors/__init__.py
scrapegen/extractors/base.py
scrapegen/extractors/content.py
scrapegen/extractors/info_extractor.py
scrapegen/extractors/__pycache__/__init__.cpython-311.pyc
scrapegen/extractors/__pycache__/base.cpython-311.pyc
scrapegen/extractors/__pycache__/content.cpython-311.pyc
scrapegen/extractors/__pycache__/info_extractor.cpython-311.pyc
scrapegen/manager/llm_manager.py
scrapegen/manager/__pycache__/llm_manager.cpython-311.pyc
scrapegen/models/__init__.py
scrapegen/models/company.py
scrapegen/models/llm.py
scrapegen/models/__pycache__/__init__.cpython-311.pyc
scrapegen/models/__pycache__/company.cpython-311.pyc
scrapegen/models/__pycache__/llm.cpython-311.pyc
scrapegen/scrapers/__init__.py
scrapegen/scrapers/anchor.py
scrapegen/scrapers/base.py
scrapegen/scrapers/url.py
scrapegen/scrapers/website.py
scrapegen/scrapers/__pycache__/__init__.cpython-311.pyc
scrapegen/scrapers/__pycache__/anchor.cpython-311.pyc
scrapegen/scrapers/__pycache__/base.cpython-311.pyc
scrapegen/scrapers/__pycache__/url.cpython-311.pyc
scrapegen/scrapers/__pycache__/website.cpython-311.pyc
scrapegen/utils/__init__.py
scrapegen/utils/normalizer.py
scrapegen/utils/url_parser.py
scrapegen/utils/__pycache__/__init__.cpython-311.pyc
scrapegen/utils/__pycache__/normalizer.cpython-311.pyc
scrapegen/utils/__pycache__/url_parser.cpython-311.pyc
scrapegen-0.1.3.dist-info/LICENSE
scrapegen-0.1.3.dist-info/METADATA
scrapegen-0.1.3.dist-info/WHEEL
scrapegen-0.1.3.dist-info/top_level.txt
scrapegen-0.1.3.dist-info/RECORD
