Metadata-Version: 2.2
Name: scrapegen
Version: 0.1.3
Summary: AI-driven web scraping framework
Author-email: Affan Shaikhsurab <affanshaikhsurab@gmail.com>
License: MIT
Project-URL: Homepage, https://github.com/affanshaikhsurab/scrapegen
Project-URL: Documentation, https://github.com/affanshaikhsurab/scrapegen/docs
Project-URL: Repository, https://github.com/affanshaikhsurab/scrapegen
Project-URL: Issues, https://github.com/affanshaikhsurab/scrapegen/issues
Keywords: AI,bing,search,scraper,web scraping,automation
Classifier: Development Status :: 3 - Alpha
Classifier: Intended Audience :: Developers
Classifier: License :: OSI Approved :: MIT License
Classifier: Programming Language :: Python :: 3
Classifier: Programming Language :: Python :: 3.7
Classifier: Programming Language :: Python :: 3.8
Classifier: Programming Language :: Python :: 3.9
Classifier: Programming Language :: Python :: 3.10
Classifier: Programming Language :: Python :: 3.11
Classifier: Operating System :: OS Independent
Requires-Python: >=3.7
License-File: LICENSE
Requires-Dist: requests>=2.26.0
Requires-Dist: beautifulsoup4>=4.9.3
Requires-Dist: langchain-google-genai>=0.0.3
Requires-Dist: pydantic>=2.0.0
Requires-Dist: lxml>=4.9.0
Dynamic: requires-python
